bedrock_syntaxer.py
bedrock_syntaxer-0.2.0.dist-info/LICENSE
bedrock_syntaxer-0.2.0.dist-info/METADATA
bedrock_syntaxer-0.2.0.dist-info/WHEEL
bedrock_syntaxer-0.2.0.dist-info/RECORD
