Metadata-Version: 2.3
Name: bedrock-syntaxer
Version: 0.2.0
Summary: A utility to force AWS Bedrock to apply the given syntax to its response.
Author: Tim Furlong
Author-email: furlong.tim@gmail.com
Requires-Python: >=3.9
Classifier: Programming Language :: Python :: 3
Classifier: Programming Language :: Python :: 3.9
Classifier: Programming Language :: Python :: 3.10
Classifier: Programming Language :: Python :: 3.11
Classifier: Programming Language :: Python :: 3.12
Classifier: Programming Language :: Python :: 3.13
Requires-Dist: boto3
